invgen/__init__.py
invgen/__main__.py
invgen/cmd.py
invgen/files.py
invgen/hosts.py
invgen/inventory.py
invgen/logging.py
invgen/metadata.py
invgen/templates.py
invgen/watcher.py
invgen-1.1.12.dist-info/METADATA
invgen-1.1.12.dist-info/WHEEL
invgen-1.1.12.dist-info/entry_points.txt
invgen-1.1.12.dist-info/top_level.txt
invgen-1.1.12.dist-info/RECORD
