Metadata-Version: 2.4
Name: invgen
Version: 1.1.12
Summary: Dynamic Ansible Inventory Generator
License: MIT License
Requires-Python: >=3.11
Requires-Dist: jinja2
Requires-Dist: pyyaml>=6.0.2
Requires-Dist: typer>=0.13.1
Requires-Dist: watchdog
